telesync/__init__.py
telesync/core.py
telesync/db.py
telesync/server.py
telesync/types.py
telesync/ui.py
telesync-0.1.0.dist-info/LICENSE
telesync-0.1.0.dist-info/METADATA
telesync-0.1.0.dist-info/WHEEL
telesync-0.1.0.dist-info/top_level.txt
telesync-0.1.0.dist-info/RECORD
