Metadata-Version: 2.1
Name: telesync
Version: 0.1.0
Summary: Python driver for H2O Q / Telesync Realtime Apps
Home-page: https://h2o.ai
Author: Prithvi Prabhu
Author-email: prithvi@h2o.ai
License: UNKNOWN
Platform: UNKNOWN
Classifier: Programming Language :: Python :: 3
Classifier: Programming Language :: Python :: 3.6
Classifier: Operating System :: OS Independent
Classifier: Development Status :: 2 - Pre-Alpha
Classifier: Intended Audience :: Developers
Classifier: License :: Other/Proprietary License
Classifier: Topic :: Database
Classifier: Topic :: Internet :: WWW/HTTP :: Dynamic Content
Classifier: Topic :: Communications :: Chat
Classifier: Topic :: Scientific/Engineering :: Visualization
Classifier: Topic :: Software Development :: Libraries :: Application Frameworks
Classifier: Topic :: Software Development :: Widget Sets
Classifier: Topic :: System :: Distributed Computing
Requires-Python: >=3.6
Requires-Dist: requests
Requires-Dist: websockets
